{
  "fetched_at": "2026-06-22 17:07 ET",
  "summary": {
    "currency": "USD",
    "net_liquidation": 111303.39,
    "gross_position_value": 102582.69,
    "total_cash_value": 8696.51,
    "available_funds": 1499.15,
    "buying_power": 1499.15,
    "dividends": 17.38,
    "leverage": "0.92"
  },
  "positions": [
    {
      "symbol": "SOXX",
      "position": 46.0,
      "average_price": 572.338046,
      "market_price": 655.0,
      "market_value": 30130.0,
      "unrealized_pnl": 3802.4499,
      "daily_pnl": 715.3,
      "currency": "USD"
    },
    {
      "symbol": "MU",
      "position": 14.0,
      "average_price": 939.032936,
      "market_price": 1240.939941,
      "market_value": 17373.15918,
      "unrealized_pnl": 4226.69808,
      "daily_pnl": 1497.29918,
      "currency": "USD"
    },
    {
      "symbol": "VSH",
      "position": 150.0,
      "average_price": 53.928515,
      "market_price": 64.120003,
      "market_value": 9618.000412,
      "unrealized_pnl": 1528.723112,
      "daily_pnl": -146.563687,
      "currency": "USD"
    },
    {
      "symbol": "AMD",
      "position": 16.0,
      "average_price": 458.474819,
      "market_price": 550.0,
      "market_value": 8800.0,
      "unrealized_pnl": 1464.4029,
      "daily_pnl": 202.08,
      "currency": "USD"
    },
    {
      "symbol": "ONTO",
      "position": 23.0,
      "average_price": 337.673917,
      "market_price": 347.850006,
      "market_value": 8000.55014,
      "unrealized_pnl": 234.05004,
      "daily_pnl": 324.07014,
      "currency": "USD"
    },
    {
      "symbol": "ON",
      "position": 39.0,
      "average_price": 123.266669,
      "market_price": 131.020004,
      "market_value": 5109.780166,
      "unrealized_pnl": 302.380066,
      "daily_pnl": 232.900166,
      "currency": "USD"
    },
    {
      "symbol": "MRVL",
      "position": 14.0,
      "average_price": 249.749121,
      "market_price": 306.5,
      "market_value": 4291.0,
      "unrealized_pnl": 794.512312,
      "daily_pnl": -64.3797,
      "currency": "USD"
    },
    {
      "symbol": "INTC",
      "position": 27.0,
      "average_price": 120.036667,
      "market_price": 140.389999,
      "market_value": 3790.529984,
      "unrealized_pnl": 549.539984,
      "daily_pnl": 172.799984,
      "currency": "USD"
    },
    {
      "symbol": "TSM",
      "position": 4.86,
      "average_price": 421.893374,
      "market_price": 467.98999,
      "market_value": 2274.431353,
      "unrealized_pnl": 224.029553,
      "daily_pnl": 28.528153,
      "currency": "USD"
    },
    {
      "symbol": "GEV",
      "position": 2.0,
      "average_price": 1068.199384,
      "market_price": 1130.0,
      "market_value": 2260.0,
      "unrealized_pnl": 123.601232,
      "daily_pnl": 31.587722,
      "currency": "USD"
    },
    {
      "symbol": "NET",
      "position": 10.0,
      "average_price": 209.81054,
      "market_price": 216.873093,
      "market_value": 2168.730926,
      "unrealized_pnl": 70.625527,
      "daily_pnl": -71.869073,
      "currency": "USD"
    },
    {
      "symbol": "NOK",
      "position": 100.0,
      "average_price": 14.890003,
      "market_price": 14.4502,
      "market_value": 1445.02001,
      "unrealized_pnl": -43.98029,
      "daily_pnl": 96.02001,
      "currency": "USD"
    },
    {
      "symbol": "CRWD",
      "position": 2.0,
      "average_price": 632.936702,
      "market_price": 676.0,
      "market_value": 1352.0,
      "unrealized_pnl": 86.126596,
      "daily_pnl": -3.3432,
      "currency": "USD"
    },
    {
      "symbol": "LITE",
      "position": 1.458,
      "average_price": 941.806447,
      "market_price": 894.294006,
      "market_value": 1303.880661,
      "unrealized_pnl": -69.273139,
      "daily_pnl": 64.580661,
      "currency": "USD"
    },
    {
      "symbol": "VRT",
      "position": 3.0,
      "average_price": 340.0,
      "market_price": 358.600006,
      "market_value": 1075.800018,
      "unrealized_pnl": 55.800018,
      "daily_pnl": 76.650018,
      "currency": "USD"
    },
    {
      "symbol": "GLW",
      "position": 5.0,
      "average_price": 177.85,
      "market_price": 211.349701,
      "market_value": 1056.748505,
      "unrealized_pnl": 167.498505,
      "daily_pnl": 82.148505,
      "currency": "USD"
    },
    {
      "symbol": "AAOI",
      "position": 6.0,
      "average_price": 178.905472,
      "market_price": 170.800003,
      "market_value": 1024.800018,
      "unrealized_pnl": -48.632814,
      "daily_pnl": 25.682918,
      "currency": "USD"
    },
    {
      "symbol": "DRAM",
      "position": 10.0,
      "average_price": 76.87,
      "market_price": 81.669998,
      "market_value": 816.699982,
      "unrealized_pnl": 47.999981,
      "daily_pnl": 49.599981,
      "currency": "USD"
    },
    {
      "symbol": "AVGO",
      "position": 1.0,
      "average_price": 429.0,
      "market_price": 393.440002,
      "market_value": 393.440002,
      "unrealized_pnl": -35.559998,
      "daily_pnl": -17.26001,
      "currency": "USD"
    },
    {
      "symbol": "DXYZ",
      "position": 8.1,
      "average_price": 67.790988,
      "market_price": 26.790001,
      "market_value": 216.999007,
      "unrealized_pnl": -332.107993,
      "daily_pnl": -8.180993,
      "currency": "USD"
    },
    {
      "symbol": "IAU",
      "position": 1.0,
      "average_price": 91.76,
      "market_price": 78.82,
      "market_value": 78.82,
      "unrealized_pnl": -12.94,
      "daily_pnl": -0.51,
      "currency": "USD"
    },
    {
      "symbol": "REMX",
      "position": 0.24,
      "average_price": 95.3,
      "market_price": 95.919899,
      "market_value": 23.020776,
      "unrealized_pnl": 0.148776,
      "daily_pnl": 0.088776,
      "currency": "USD"
    },
    {
      "symbol": "GOOGL",
      "position": 0.0,
      "average_price": 0.0,
      "market_price": 347.119995,
      "market_value": 0.0,
      "unrealized_pnl": 4.3e-05,
      "daily_pnl": -82.3494,
      "currency": "USD"
    }
  ],
  "trades": [
    {
      "symbol": "ON",
      "side": "BUY",
      "size": 5.0,
      "price": 130.5,
      "trade_time": "2026-06-22T14:49:21Z"
    },
    {
      "symbol": "VSH",
      "side": "SELL",
      "size": 0.7,
      "price": 64.02,
      "trade_time": "2026-06-22T14:47:25Z"
    },
    {
      "symbol": "VSH",
      "side": "SELL",
      "size": 31.0,
      "price": 64.0,
      "trade_time": "2026-06-22T14:47:02Z"
    },
    {
      "symbol": "GOOGL",
      "side": "SELL",
      "size": 4.0,
      "price": 347.7,
      "trade_time": "2026-06-22T14:44:46Z"
    },
    {
      "symbol": "ON",
      "side": "BUY",
      "size": 5.0,
      "price": 130.5,
      "trade_time": "2026-06-22T14:43:41Z"
    },
    {
      "symbol": "MRVL",
      "side": "SELL",
      "size": 3.0,
      "price": 308.5,
      "trade_time": "2026-06-22T14:36:06Z"
    },
    {
      "symbol": "CRWD",
      "side": "SELL",
      "size": 3.0,
      "price": 690.0,
      "trade_time": "2026-06-22T14:32:22Z"
    },
    {
      "symbol": "GEV",
      "side": "BUY",
      "size": 0.813,
      "price": 1119.5114,
      "trade_time": "2026-06-22T14:01:39Z"
    },
    {
      "symbol": "ON",
      "side": "BUY",
      "size": 5.0,
      "price": 130.0,
      "trade_time": "2026-06-22T13:53:34Z"
    },
    {
      "symbol": "AAOI",
      "side": "SELL",
      "size": 5.0,
      "price": 156.45,
      "trade_time": "2026-06-22T13:43:59Z"
    },
    {
      "symbol": "NOK",
      "side": "SELL",
      "size": 100.0,
      "price": 13.55,
      "trade_time": "2026-06-18T19:29:03Z"
    },
    {
      "symbol": "ON",
      "side": "BUY",
      "size": 6.0,
      "price": 120.0,
      "trade_time": "2026-06-18T18:33:02Z"
    },
    {
      "symbol": "DRAM",
      "side": "BUY",
      "size": 10.0,
      "price": 76.77,
      "trade_time": "2026-06-18T17:01:42Z"
    },
    {
      "symbol": "SOXX",
      "side": "BUY",
      "size": 3.0,
      "price": 637.0,
      "trade_time": "2026-06-18T17:01:31Z"
    },
    {
      "symbol": "INTC",
      "side": "BUY",
      "size": 1.0,
      "price": 130.0,
      "trade_time": "2026-06-18T14:39:39Z"
    },
    {
      "symbol": "ON",
      "side": "BUY",
      "size": 3.0,
      "price": 121.2,
      "trade_time": "2026-06-18T14:36:59Z"
    },
    {
      "symbol": "ONTO",
      "side": "BUY",
      "size": 2.0,
      "price": 337.5,
      "trade_time": "2026-06-18T14:36:24Z"
    },
    {
      "symbol": "NOK",
      "side": "SELL",
      "size": 100.0,
      "price": 14.0,
      "trade_time": "2026-06-17T15:46:29Z"
    },
    {
      "symbol": "INTC",
      "side": "BUY",
      "size": 1.0,
      "price": 121.0,
      "trade_time": "2026-06-17T15:40:31Z"
    },
    {
      "symbol": "GOOGL",
      "side": "SELL",
      "size": 0.374,
      "price": 363.52,
      "trade_time": "2026-06-17T15:06:24Z"
    },
    {
      "symbol": "GOOGL",
      "side": "SELL",
      "size": 2.0,
      "price": 363.5,
      "trade_time": "2026-06-17T15:06:20Z"
    },
    {
      "symbol": "MU",
      "side": "SELL",
      "size": 0.5,
      "price": 1036.86,
      "trade_time": "2026-06-17T15:00:22Z"
    },
    {
      "symbol": "MU",
      "side": "SELL",
      "size": 2.0,
      "price": 1036.869,
      "trade_time": "2026-06-17T15:00:22Z"
    },
    {
      "symbol": "NOK",
      "side": "SELL",
      "size": 170.0,
      "price": 13.9207,
      "trade_time": "2026-06-17T14:55:44Z"
    },
    {
      "symbol": "ONTO",
      "side": "BUY",
      "size": 1.0,
      "price": 330.0,
      "trade_time": "2026-06-17T13:30:00Z"
    },
    {
      "symbol": "AMD",
      "side": "BUY",
      "size": 1.0,
      "price": 549.0,
      "trade_time": "2026-06-16T10:52:31Z"
    },
    {
      "symbol": "INTC",
      "side": "BUY",
      "size": 2.0,
      "price": 128.0,
      "trade_time": "2026-06-15T16:02:02Z"
    },
    {
      "symbol": "SOXX",
      "side": "SELL",
      "size": 2.0,
      "price": 622.0,
      "trade_time": "2026-06-15T14:57:09Z"
    },
    {
      "symbol": "NET",
      "side": "BUY",
      "size": 0.09,
      "price": 236.68,
      "trade_time": "2026-06-15T14:41:47Z"
    },
    {
      "symbol": "NET",
      "side": "BUY",
      "size": 1.0,
      "price": 237.0,
      "trade_time": "2026-06-15T14:40:07Z"
    },
    {
      "symbol": "ONTO",
      "side": "BUY",
      "size": 15.0,
      "price": 338.5,
      "trade_time": "2026-06-15T13:36:23Z"
    },
    {
      "symbol": "ONTO",
      "side": "BUY",
      "size": 5.0,
      "price": 336.0,
      "trade_time": "2026-06-15T01:21:56Z"
    },
    {
      "symbol": "CRWD",
      "side": "BUY",
      "size": 0.355,
      "price": 681.99,
      "trade_time": "2026-06-12T19:52:26Z"
    },
    {
      "symbol": "CRWD",
      "side": "BUY",
      "size": 1.0,
      "price": 682.0,
      "trade_time": "2026-06-12T19:50:47Z"
    },
    {
      "symbol": "NOK",
      "side": "BUY",
      "size": 100.0,
      "price": 14.88,
      "trade_time": "2026-06-12T19:49:45Z"
    },
    {
      "symbol": "INTC",
      "side": "BUY",
      "size": 8.0,
      "price": 125.5,
      "trade_time": "2026-06-12T18:02:27Z"
    },
    {
      "symbol": "MU",
      "side": "BUY",
      "size": 0.5,
      "price": 994.96,
      "trade_time": "2026-06-12T18:01:32Z"
    },
    {
      "symbol": "SOXX",
      "side": "BUY",
      "size": 10.0,
      "price": 600.0,
      "trade_time": "2026-06-12T17:55:51Z"
    },
    {
      "symbol": "VRT",
      "side": "SELL",
      "size": 0.29,
      "price": 300.04,
      "trade_time": "2026-06-12T17:45:24Z"
    },
    {
      "symbol": "VRT",
      "side": "SELL",
      "size": 2.0,
      "price": 300.0,
      "trade_time": "2026-06-12T17:42:07Z"
    },
    {
      "symbol": "ON",
      "side": "BUY",
      "size": 5.0,
      "price": 117.0,
      "trade_time": "2026-06-12T17:31:32Z"
    },
    {
      "symbol": "MU",
      "side": "SELL",
      "size": 0.3,
      "price": 995.97,
      "trade_time": "2026-06-12T16:48:30Z"
    },
    {
      "symbol": "MU",
      "side": "BUY",
      "size": 0.3,
      "price": 992.94,
      "trade_time": "2026-06-12T16:17:59Z"
    },
    {
      "symbol": "MRVL",
      "side": "BUY",
      "size": 1.0,
      "price": 284.0,
      "trade_time": "2026-06-12T16:17:55Z"
    },
    {
      "symbol": "NOK",
      "side": "BUY",
      "size": 100.0,
      "price": 15.0,
      "trade_time": "2026-06-12T15:33:11Z"
    },
    {
      "symbol": "MU",
      "side": "BUY",
      "size": 0.084,
      "price": 998.85,
      "trade_time": "2026-06-12T15:32:43Z"
    },
    {
      "symbol": "MRVL",
      "side": "BUY",
      "size": 3.0,
      "price": 287.335,
      "trade_time": "2026-06-12T15:30:04Z"
    },
    {
      "symbol": "AAOI",
      "side": "BUY",
      "size": 0.897,
      "price": 171.6948,
      "trade_time": "2026-06-12T15:30:02Z"
    },
    {
      "symbol": "AAOI",
      "side": "BUY",
      "size": 5.0,
      "price": 172.0,
      "trade_time": "2026-06-12T15:30:00Z"
    },
    {
      "symbol": "MU",
      "side": "BUY",
      "size": 1.0,
      "price": 999.0,
      "trade_time": "2026-06-12T15:28:44Z"
    },
    {
      "symbol": "ON",
      "side": "BUY",
      "size": 7.0,
      "price": 118.0,
      "trade_time": "2026-06-12T15:20:12Z"
    },
    {
      "symbol": "VSH",
      "side": "BUY",
      "size": 20.0,
      "price": 58.8,
      "trade_time": "2026-06-12T15:18:47Z"
    },
    {
      "symbol": "AVGO",
      "side": "SELL",
      "size": 0.103,
      "price": 380.25,
      "trade_time": "2026-06-12T14:35:02Z"
    },
    {
      "symbol": "AVGO",
      "side": "SELL",
      "size": 2.0,
      "price": 380.15,
      "trade_time": "2026-06-12T14:34:54Z"
    },
    {
      "symbol": "ON",
      "side": "BUY",
      "size": 3.0,
      "price": 116.6,
      "trade_time": "2026-06-12T14:32:29Z"
    },
    {
      "symbol": "VSH",
      "side": "BUY",
      "size": 15.0,
      "price": 56.21,
      "trade_time": "2026-06-12T14:26:16Z"
    },
    {
      "symbol": "ETN",
      "side": "SELL",
      "size": 10.0,
      "price": 397.5,
      "trade_time": "2026-06-12T13:31:24Z"
    },
    {
      "symbol": "VSH",
      "side": "BUY",
      "size": 15.0,
      "price": 57.8,
      "trade_time": "2026-06-12T12:07:02Z"
    },
    {
      "symbol": "GOOGL",
      "side": "BUY",
      "size": 2.0,
      "price": 360.0,
      "trade_time": "2026-06-12T01:11:49Z"
    },
    {
      "symbol": "VSH",
      "side": "BUY",
      "size": 13.0,
      "price": 58.3,
      "trade_time": "2026-06-11T13:59:55Z"
    },
    {
      "symbol": "SOXX",
      "side": "SELL",
      "size": 10.0,
      "price": 556.0,
      "trade_time": "2026-06-11T13:28:07Z"
    },
    {
      "symbol": "SOXX",
      "side": "SELL",
      "size": 10.0,
      "price": 555.0,
      "trade_time": "2026-06-11T13:10:42Z"
    },
    {
      "symbol": "SOXX",
      "side": "SELL",
      "size": 5.0,
      "price": 555.0,
      "trade_time": "2026-06-11T13:10:42Z"
    },
    {
      "symbol": "SOXX",
      "side": "SELL",
      "size": 10.0,
      "price": 558.0,
      "trade_time": "2026-06-11T11:48:41Z"
    },
    {
      "symbol": "GEV",
      "side": "SELL",
      "size": 1.0,
      "price": 891.5,
      "trade_time": "2026-06-11T11:47:04Z"
    },
    {
      "symbol": "VRT",
      "side": "SELL",
      "size": 2.0,
      "price": 289.58,
      "trade_time": "2026-06-11T11:44:20Z"
    },
    {
      "symbol": "AVGO",
      "side": "SELL",
      "size": 2.0,
      "price": 375.5,
      "trade_time": "2026-06-11T11:43:13Z"
    },
    {
      "symbol": "REMX",
      "side": "SELL",
      "size": 3.0,
      "price": 88.2,
      "trade_time": "2026-06-11T11:42:27Z"
    },
    {
      "symbol": "NOK",
      "side": "BUY",
      "size": 200.0,
      "price": 14.95,
      "trade_time": "2026-06-08T15:22:24Z"
    },
    {
      "symbol": "AMD",
      "side": "BUY",
      "size": 2.0,
      "price": 486.94,
      "trade_time": "2026-06-08T14:31:46Z"
    },
    {
      "symbol": "AMD",
      "side": "BUY",
      "size": 0.607,
      "price": 487.13,
      "trade_time": "2026-06-08T14:31:46Z"
    },
    {
      "symbol": "NOK",
      "side": "SELL",
      "size": 100.0,
      "price": 14.835,
      "trade_time": "2026-06-08T14:29:38Z"
    },
    {
      "symbol": "MRVL",
      "side": "BUY",
      "size": 5.0,
      "price": 293.0,
      "trade_time": "2026-06-08T14:28:22Z"
    },
    {
      "symbol": "MU",
      "side": "BUY",
      "size": 4.0,
      "price": 937.6,
      "trade_time": "2026-06-08T14:27:09Z"
    },
    {
      "symbol": "SOXX",
      "side": "SELL",
      "size": 0.645,
      "price": 568.01,
      "trade_time": "2026-06-08T14:26:16Z"
    },
    {
      "symbol": "SOXX",
      "side": "SELL",
      "size": 14.0,
      "price": 568.05,
      "trade_time": "2026-06-08T14:26:16Z"
    },
    {
      "symbol": "MU",
      "side": "BUY",
      "size": 8.0,
      "price": 928.0,
      "trade_time": "2026-06-08T00:40:32Z"
    },
    {
      "symbol": "SOXX",
      "side": "BUY",
      "size": 60.0,
      "price": 558.0,
      "trade_time": "2026-06-08T00:33:22Z"
    },
    {
      "symbol": "SOXX",
      "side": "BUY",
      "size": 20.0,
      "price": 555.49,
      "trade_time": "2026-06-08T00:22:36Z"
    },
    {
      "symbol": "SOXX",
      "side": "BUY",
      "size": 1.0,
      "price": 556.81,
      "trade_time": "2026-06-08T00:17:55Z"
    },
    {
      "symbol": "GLW",
      "side": "SELL",
      "size": 1.0,
      "price": 190.0,
      "trade_time": "2026-06-05T14:51:57Z"
    },
    {
      "symbol": "TSM",
      "side": "SELL",
      "size": 0.54,
      "price": 430.27,
      "trade_time": "2026-06-05T14:15:52Z"
    },
    {
      "symbol": "MRVL",
      "side": "SELL",
      "size": 0.935,
      "price": 290.55,
      "trade_time": "2026-06-05T13:51:10Z"
    },
    {
      "symbol": "MRVL",
      "side": "SELL",
      "size": 2.0,
      "price": 290.47,
      "trade_time": "2026-06-05T13:51:06Z"
    },
    {
      "symbol": "NOK",
      "side": "SELL",
      "size": 100.0,
      "price": 15.13,
      "trade_time": "2026-06-05T13:50:00Z"
    },
    {
      "symbol": "VSH",
      "side": "SELL",
      "size": 100.0,
      "price": 58.34,
      "trade_time": "2026-06-05T13:49:55Z"
    },
    {
      "symbol": "GLW",
      "side": "SELL",
      "size": 7.0,
      "price": 181.33,
      "trade_time": "2026-06-05T13:47:30Z"
    },
    {
      "symbol": "GEV",
      "side": "SELL",
      "size": 0.243,
      "price": 945.64,
      "trade_time": "2026-06-05T13:47:05Z"
    },
    {
      "symbol": "LITE",
      "side": "SELL",
      "size": 0.162,
      "price": 901.67,
      "trade_time": "2026-06-05T13:46:25Z"
    },
    {
      "symbol": "VRT",
      "side": "SELL",
      "size": 0.81,
      "price": 307.72,
      "trade_time": "2026-06-05T13:46:24Z"
    },
    {
      "symbol": "MRVL",
      "side": "SELL",
      "size": 0.215,
      "price": 292.73,
      "trade_time": "2026-06-05T13:44:24Z"
    },
    {
      "symbol": "MRVL",
      "side": "SELL",
      "size": 1.0,
      "price": 292.48,
      "trade_time": "2026-06-05T13:44:22Z"
    },
    {
      "symbol": "SOXX",
      "side": "SELL",
      "size": 0.405,
      "price": 571.7,
      "trade_time": "2026-06-05T13:44:22Z"
    },
    {
      "symbol": "CRWD",
      "side": "SELL",
      "size": 0.405,
      "price": 697.47,
      "trade_time": "2026-06-05T13:44:10Z"
    },
    {
      "symbol": "VSH",
      "side": "SELL",
      "size": 24.0,
      "price": 58.85,
      "trade_time": "2026-06-05T13:43:39Z"
    },
    {
      "symbol": "VSH",
      "side": "SELL",
      "size": 0.3,
      "price": 58.86,
      "trade_time": "2026-06-05T13:43:39Z"
    },
    {
      "symbol": "AMD",
      "side": "SELL",
      "size": 0.377,
      "price": 495.72,
      "trade_time": "2026-06-05T13:43:38Z"
    },
    {
      "symbol": "MU",
      "side": "SELL",
      "size": 0.324,
      "price": 940.57,
      "trade_time": "2026-06-05T13:43:37Z"
    },
    {
      "symbol": "AMD",
      "side": "SELL",
      "size": 1.0,
      "price": 495.72,
      "trade_time": "2026-06-05T13:43:34Z"
    },
    {
      "symbol": "AAOI",
      "side": "SELL",
      "size": 0.567,
      "price": 183.13,
      "trade_time": "2026-06-05T13:43:29Z"
    },
    {
      "symbol": "AVGO",
      "side": "SELL",
      "size": 0.567,
      "price": 401.36,
      "trade_time": "2026-06-05T13:43:29Z"
    },
    {
      "symbol": "GOOGL",
      "side": "SELL",
      "size": 0.486,
      "price": 370.2,
      "trade_time": "2026-06-05T13:43:24Z"
    },
    {
      "symbol": "REMX",
      "side": "SELL",
      "size": 0.36,
      "price": 92.62,
      "trade_time": "2026-06-05T13:36:37Z"
    },
    {
      "symbol": "VSH",
      "side": "SELL",
      "size": 24.0,
      "price": 59.76,
      "trade_time": "2026-06-05T13:35:59Z"
    },
    {
      "symbol": "CRWD",
      "side": "SELL",
      "size": 0.45,
      "price": 692.75,
      "trade_time": "2026-06-05T13:35:53Z"
    },
    {
      "symbol": "MU",
      "side": "SELL",
      "size": 0.36,
      "price": 952.28,
      "trade_time": "2026-06-05T13:35:52Z"
    },
    {
      "symbol": "VSH",
      "side": "SELL",
      "size": 3.0,
      "price": 59.76,
      "trade_time": "2026-06-05T13:35:52Z"
    },
    {
      "symbol": "AAOI",
      "side": "SELL",
      "size": 0.63,
      "price": 186.3,
      "trade_time": "2026-06-05T13:35:51Z"
    },
    {
      "symbol": "AMD",
      "side": "SELL",
      "size": 0.53,
      "price": 498.87,
      "trade_time": "2026-06-05T13:35:51Z"
    },
    {
      "symbol": "AMD",
      "side": "SELL",
      "size": 1.0,
      "price": 499.43,
      "trade_time": "2026-06-05T13:35:51Z"
    },
    {
      "symbol": "AVGO",
      "side": "SELL",
      "size": 0.63,
      "price": 403.12,
      "trade_time": "2026-06-05T13:35:51Z"
    },
    {
      "symbol": "DXYZ",
      "side": "SELL",
      "size": 0.9,
      "price": 45.17,
      "trade_time": "2026-06-05T13:35:51Z"
    },
    {
      "symbol": "GEV",
      "side": "SELL",
      "size": 0.27,
      "price": 945.0,
      "trade_time": "2026-06-05T13:35:51Z"
    },
    {
      "symbol": "LITE",
      "side": "SELL",
      "size": 0.18,
      "price": 919.85,
      "trade_time": "2026-06-05T13:35:51Z"
    },
    {
      "symbol": "MRVL",
      "side": "SELL",
      "size": 1.0,
      "price": 296.83,
      "trade_time": "2026-06-05T13:35:51Z"
    },
    {
      "symbol": "MRVL",
      "side": "SELL",
      "size": 0.35,
      "price": 297.0,
      "trade_time": "2026-06-05T13:35:51Z"
    },
    {
      "symbol": "NET",
      "side": "SELL",
      "size": 0.99,
      "price": 264.01,
      "trade_time": "2026-06-05T13:35:51Z"
    },
    {
      "symbol": "SOXX",
      "side": "SELL",
      "size": 0.45,
      "price": 575.48,
      "trade_time": "2026-06-05T13:35:51Z"
    },
    {
      "symbol": "VRT",
      "side": "SELL",
      "size": 0.9,
      "price": 309.64,
      "trade_time": "2026-06-05T13:35:51Z"
    },
    {
      "symbol": "GOOGL",
      "side": "SELL",
      "size": 0.54,
      "price": 367.67,
      "trade_time": "2026-06-05T13:35:50Z"
    },
    {
      "symbol": "VSH",
      "side": "SELL",
      "size": 30.0,
      "price": 59.33,
      "trade_time": "2026-06-05T13:35:29Z"
    },
    {
      "symbol": "GEV",
      "side": "SELL",
      "size": 0.3,
      "price": 950.0,
      "trade_time": "2026-06-05T13:33:31Z"
    },
    {
      "symbol": "NET",
      "side": "SELL",
      "size": 1.0,
      "price": 267.52,
      "trade_time": "2026-06-05T13:31:17Z"
    },
    {
      "symbol": "NET",
      "side": "SELL",
      "size": 0.1,
      "price": 267.64,
      "trade_time": "2026-06-05T13:31:17Z"
    },
    {
      "symbol": "GOOGL",
      "side": "SELL",
      "size": 0.6,
      "price": 366.5,
      "trade_time": "2026-06-05T13:30:57Z"
    },
    {
      "symbol": "NOK",
      "side": "SELL",
      "size": 30.0,
      "price": 15.63,
      "trade_time": "2026-06-05T13:30:14Z"
    },
    {
      "symbol": "MU",
      "side": "SELL",
      "size": 0.4,
      "price": 943.23,
      "trade_time": "2026-06-05T13:30:09Z"
    },
    {
      "symbol": "SOXX",
      "side": "SELL",
      "size": 0.5,
      "price": 577.59,
      "trade_time": "2026-06-05T13:30:08Z"
    },
    {
      "symbol": "MRVL",
      "side": "SELL",
      "size": 0.5,
      "price": 298.05,
      "trade_time": "2026-06-05T13:30:07Z"
    },
    {
      "symbol": "TSM",
      "side": "SELL",
      "size": 0.6,
      "price": 430.82,
      "trade_time": "2026-06-05T13:30:07Z"
    },
    {
      "symbol": "AMD",
      "side": "SELL",
      "size": 0.7,
      "price": 500.85,
      "trade_time": "2026-06-05T13:30:05Z"
    },
    {
      "symbol": "REMX",
      "side": "SELL",
      "size": 0.4,
      "price": 93.38,
      "trade_time": "2026-06-05T13:30:05Z"
    },
    {
      "symbol": "AMD",
      "side": "SELL",
      "size": 1.0,
      "price": 500.44,
      "trade_time": "2026-06-05T13:30:04Z"
    },
    {
      "symbol": "AVGO",
      "side": "SELL",
      "size": 0.7,
      "price": 409.77,
      "trade_time": "2026-06-05T13:30:04Z"
    },
    {
      "symbol": "CRWD",
      "side": "SELL",
      "size": 0.5,
      "price": 698.76,
      "trade_time": "2026-06-05T13:30:04Z"
    },
    {
      "symbol": "MRVL",
      "side": "SELL",
      "size": 1.0,
      "price": 297.31,
      "trade_time": "2026-06-05T13:30:04Z"
    },
    {
      "symbol": "AAOI",
      "side": "SELL",
      "size": 0.7,
      "price": 190.98,
      "trade_time": "2026-06-05T13:30:03Z"
    },
    {
      "symbol": "DXYZ",
      "side": "SELL",
      "size": 1.0,
      "price": 44.9,
      "trade_time": "2026-06-05T13:30:01Z"
    },
    {
      "symbol": "LITE",
      "side": "SELL",
      "size": 0.2,
      "price": 911.49,
      "trade_time": "2026-06-05T13:30:01Z"
    },
    {
      "symbol": "VRT",
      "side": "SELL",
      "size": 1.0,
      "price": 313.36,
      "trade_time": "2026-06-05T13:30:01Z"
    },
    {
      "symbol": "VSH",
      "side": "SELL",
      "size": 100.0,
      "price": 60.87,
      "trade_time": "2026-06-05T13:19:26Z"
    },
    {
      "symbol": "SOXX",
      "side": "SELL",
      "size": 10.0,
      "price": 578.6,
      "trade_time": "2026-06-05T13:18:12Z"
    },
    {
      "symbol": "INTC",
      "side": "SELL",
      "size": 20.0,
      "price": 107.2,
      "trade_time": "2026-06-05T13:17:29Z"
    },
    {
      "symbol": "AAOI",
      "side": "SELL",
      "size": 3.0,
      "price": 192.51,
      "trade_time": "2026-06-05T13:16:06Z"
    },
    {
      "symbol": "NOK",
      "side": "SELL",
      "size": 130.0,
      "price": 15.74,
      "trade_time": "2026-06-05T13:12:30Z"
    },
    {
      "symbol": "LITE",
      "side": "SELL",
      "size": 3.0,
      "price": 901.0,
      "trade_time": "2026-06-05T13:11:24Z"
    },
    {
      "symbol": "DRAM",
      "side": "SELL",
      "size": 20.0,
      "price": 61.05,
      "trade_time": "2026-06-05T13:01:14Z"
    },
    {
      "symbol": "DRAM",
      "side": "SELL",
      "size": 20.0,
      "price": 61.05,
      "trade_time": "2026-06-05T13:01:14Z"
    },
    {
      "symbol": "MU",
      "side": "SELL",
      "size": 3.0,
      "price": 948.06,
      "trade_time": "2026-06-05T12:38:12Z"
    },
    {
      "symbol": "DRAM",
      "side": "SELL",
      "size": 20.0,
      "price": 61.13,
      "trade_time": "2026-06-05T12:37:34Z"
    }
  ]
}